portwarden/__init__.py
portwarden/portwarden.py
portwarden-1.0.2.dist-info/licenses/LICENSE
portwarden-1.0.2.dist-info/METADATA
portwarden-1.0.2.dist-info/WHEEL
portwarden-1.0.2.dist-info/entry_points.txt
portwarden-1.0.2.dist-info/top_level.txt
portwarden-1.0.2.dist-info/RECORD
