Metadata-Version: 2.4
Name: PortWarden
Version: 1.0.2
Summary: A fast multi-threaded TCP port scanner with JSON output.
Home-page: https://github.com/nfs-tech-bd/PortWarden 
Author: B14CK-KN1GH7
Author-email: nafisfuad340@gmail.com
License: MIT
Classifier: Programming Language :: Python :: 3
Classifier: License :: OSI Approved :: MIT License
Classifier: Operating System :: OS Independent
Classifier: Intended Audience :: Developers
Classifier: Topic :: Security
Classifier: Environment :: Console
Requires-Python: >=3.6
License-File: LICENSE
Dynamic: author
Dynamic: author-email
Dynamic: classifier
Dynamic: description
Dynamic: description-content-type
Dynamic: home-page
Dynamic: license
Dynamic: license-file
Dynamic: requires-python
Dynamic: summary
